README.rst
setup.py
django_fsu/__init__.py
django_fsu/tests.py
django_fsu.egg-info/PKG-INFO
django_fsu.egg-info/SOURCES.txt
django_fsu.egg-info/dependency_links.txt
django_fsu.egg-info/top_level.txt